{    "contentType": "application/gliffy+json",    "embeddedResources": {        "index": 0,        "resources": []    },    "metadata": {        "exportBorder": false,        "revision": 0,        "title": "untitled"    },    "stage": {        "autoFit": true,        "background": "#FFFFFF",        "drawingGuidesOn": true,        "exportBorder": false,        "gridOn": true,        "height": 0,        "lineStyles": {},        "maxHeight": 5000,        "maxWidth": 5000,        "nodeIndex": 0,        "objects": [],        "pageBreaksOn": false,        "printGridOn": false,        "printPaper": "LETTER",        "printPortrait": true,        "printShrinkToFit": false,        "shapeStyles": {},        "snapToGrid": true,        "textStyles": {},        "themeData": null,        "width": 0    },    "version": "1.1"}